java -jar jasmin.jar Main.j fref_of_Io.j ref_of_I.j
.class public Main
.super java/lang/Object

; standard initializer
.method public <init>()V
    aload_0
    invokenonvirtual java/lang/Object/<init>()V
    return
.end method

.method public static main([Ljava/lang/String;)V
    ; set limits used by this method
    .limit locals 10
    .limit stack 256

    ; Move null to local main variable
    aconst_null
    astore 2

    ; START

new fref_of_Io
dup
invokespecial fref_of_Io/<init>()V
dup
aload 2
putfield fref_of_Io/sl Ljava/lang/Object;
astore 2
aload 2
new ref_of_I
dup
invokespecial ref_of_I/<init>()V
dup
sipush 5
putfield ref_of_I/v I
putfield fref_of_Io/s_0 Lref_of_I;
LWhileStart0:
aload 2
getfield fref_of_Io/s_0 Lref_of_I;
getfield ref_of_I/v I
sipush 0
isub
ifgt LWhileTL1
goto LWhileFL2
LWhileTL1:
aload 2
getfield fref_of_Io/s_0 Lref_of_I;
getfield ref_of_I/v I
dup
getstatic java/lang/System/out Ljava/io/PrintStream;
swap
invokestatic java/lang/String/valueOf(I)Ljava/lang/String;
invokevirtual java/io/PrintStream/println(Ljava/lang/String;)V
pop
aload 2
getfield fref_of_Io/s_0 Lref_of_I;
dup
aload 2
getfield fref_of_Io/s_0 Lref_of_I;
getfield ref_of_I/v I
sipush 1
isub
putfield ref_of_I/v I
getfield ref_of_I/v I
pop
aload 2
getfield fref_of_Io/s_0 Lref_of_I;
getfield ref_of_I/v I
dup
getstatic java/lang/System/out Ljava/io/PrintStream;
swap
invokestatic java/lang/String/valueOf(I)Ljava/lang/String;
invokevirtual java/io/PrintStream/println(Ljava/lang/String;)V
pop
goto LWhileStart0
LWhileFL2:
sipush 0
aload 2
getfield fref_of_Io/sl Ljava/lang/Object;
astore 2
    ; END

    ; Remove from stack expression value
    pop

    return
.end method
