java -jar jasmin.jar Main.j fIIo.j
.class public Main
.super java/lang/Object

; standard initializer
.method public <init>()V
    aload_0
    invokenonvirtual java/lang/Object/<init>()V
    return
.end method

.method public static main([Ljava/lang/String;)V
    ; set limits used by this method
    .limit locals 10
    .limit stack 256

    ; Move null to local main variable
    aconst_null
    astore 2

    ; START

new fIIo
dup
invokespecial fIIo/<init>()V
dup
aload 2
putfield fIIo/sl Ljava/lang/Object;
astore 2
aload 2
sipush 2
putfield fIIo/s_0 I
aload 2
sipush 3
putfield fIIo/s_1 I
aload 2
getfield fIIo/s_0 I
aload 2
getfield fIIo/s_1 I
iadd
aload 2
getfield fIIo/sl Ljava/lang/Object;
astore 2
dup
getstatic java/lang/System/out Ljava/io/PrintStream;
swap
invokestatic java/lang/String/valueOf(I)Ljava/lang/String;
invokevirtual java/io/PrintStream/println(Ljava/lang/String;)V
    ; END

    ; Remove from stack expression value
    pop

    return
.end method
