java -jar jasmin.jar Main.j fclosure_1o.j fIfclosure_1o.j closure_1.j closure_interface_I_I.j
.class public Main
.super java/lang/Object

; standard initializer
.method public <init>()V
    aload_0
    invokenonvirtual java/lang/Object/<init>()V
    return
.end method

.method public static main([Ljava/lang/String;)V
    ; set limits used by this method
    .limit locals 10
    .limit stack 256

    ; Move null to local main variable
    aconst_null
    astore 2

    ; START

new fclosure_1o
dup
invokespecial fclosure_1o/<init>()V
dup
aload 2
putfield fclosure_1o/sl Ljava/lang/Object;
astore 2
aload 2
new closure_1
dup
invokespecial closure_1/<init>()V
dup
aload 2
putfield closure_1/sl Lfclosure_1o;
putfield fclosure_1o/s_0 Lclosure_1;
aload 2
getfield fclosure_1o/s_0 Lclosure_1;
checkcast closure_interface_I_I
sipush 2
invokeinterface closure_interface_I_I/apply(I)I 2
aload 2
getfield fclosure_1o/s_0 Lclosure_1;
checkcast closure_interface_I_I
sipush 3
invokeinterface closure_interface_I_I/apply(I)I 2
iadd
dup
getstatic java/lang/System/out Ljava/io/PrintStream;
swap
invokestatic java/lang/String/valueOf(I)Ljava/lang/String;
invokevirtual java/io/PrintStream/println(Ljava/lang/String;)V
aload 2
getfield fclosure_1o/sl Ljava/lang/Object;
astore 2
    ; END

    ; Remove from stack expression value
    pop

    return
.end method
